Metadata-Version: 1.1
Name: zoocli
Version: 0.2.1
Summary: Interactive ZooKeeper CLI tool.
Home-page: https://github.com/m110/zoocli
Author: Milosz Smolka
Author-email: m110@m110.pl
License: UNKNOWN
Platform: UNKNOWN
Classifier: Development Status :: 3 - Alpha
Classifier: Environment :: Console
Classifier: Intended Audience :: End Users/Desktop
Classifier: Intended Audience :: Developers
Classifier: Intended Audience :: System Administrators
Classifier: License :: OSI Approved :: MIT License
Classifier: Operating System :: POSIX
Classifier: Programming Language :: Python :: 3.4
Classifier: Topic :: System :: Systems Administration
